pyCICY/__init__.py
pyCICY/pyCICY.py
pyCICY-0.5.2.dist-info/LICENSE
pyCICY-0.5.2.dist-info/METADATA
pyCICY-0.5.2.dist-info/WHEEL
pyCICY-0.5.2.dist-info/top_level.txt
pyCICY-0.5.2.dist-info/RECORD
