Metadata-Version: 2.1
Name: pyCICY
Version: 0.5.2
Summary: A python CICY toolkit
Home-page: https://github.com/robin-schneider/CICY
Author: Robin Schneider
Author-email: robin.schneider@physics.uu.se
License: UNKNOWN
Platform: UNKNOWN
Classifier: Programming Language :: Python :: 2.7
Classifier: Programming Language :: Python :: 3
Classifier: License :: OSI Approved :: GNU General Public License v3 (GPLv3)
Classifier: Operating System :: OS Independent
Classifier: Topic :: Scientific/Engineering :: Mathematics
Classifier: Topic :: Scientific/Engineering :: Physics
Requires-Dist: numpy
Requires-Dist: scipy
Requires-Dist: sympy
Requires-Dist: texttable
Requires-Dist: matplotlib
